redditeasy/__init__.py
redditeasy/base.py
redditeasy/client.py
redditeasy/exceptions.py
redditeasy/reddit.py
redditeasy/subreddit.py
redditeasy/user.py
redditeasy/classes/__init__.py
redditeasy/classes/client_data.py
redditeasy/classes/media.py
redditeasy/classes/post.py
redditeasy/exceptions/__init__.py
redditeasy/exceptions/exceptions.py
redditeasy/types/__init__.py
redditeasy/types/content_type.py
redditeasy/utils/__init__.py
redditeasy/utils/utils.py
redditeasy-4.0.0.dist-info/LICENSE
redditeasy-4.0.0.dist-info/METADATA
redditeasy-4.0.0.dist-info/WHEEL
redditeasy-4.0.0.dist-info/top_level.txt
redditeasy-4.0.0.dist-info/RECORD
