Metadata-Version: 2.1
Name: redditeasy
Version: 4.0.0
Summary: RedditEasy is an API wrapper for getting posts using the Reddit JSON API with both sync and async options
Home-page: https://redditeasy.readthedocs.io/en/latest/
Author: MakufonSkifto
License: UNKNOWN
Project-URL: Documentation, https://redditeasy.readthedocs.io/en/latest/
Project-URL: Issue tracker, https://github.com/MakufonSkifto/RedditEasy/issues
Project-URL: Source, https://github.com/MakufonSkifto/RedditEasy
Keywords: reddit api async meme redditapi redditbot asyncreddit redditposts praw discord.py bot
Platform: UNKNOWN
Classifier: Programming Language :: Python :: 3
Classifier: Programming Language :: Python :: 3.6
Classifier: Programming Language :: Python :: 3.7
Classifier: Programming Language :: Python :: 3.8
Classifier: Programming Language :: Python :: 3.9
Classifier: Programming Language :: Python :: 3.10
Classifier: License :: OSI Approved :: GNU General Public License v3 (GPLv3)
Classifier: Operating System :: Microsoft :: Windows
Classifier: Operating System :: MacOS
Classifier: Operating System :: POSIX :: Linux
Requires-Python: >=3.6
License-File: LICENSE
Requires-Dist: aiohttp
Requires-Dist: urllib3
Requires-Dist: orjson
